pipeline/__init__.py
pipeline/eval.py
pipeline/models.py
pipeline/utils.py
pipeline/clipseg/__init__.py
pipeline/clipseg/evaluation_utils.py
pipeline/clipseg/general_utils.py
pipeline/clipseg/metrics.py
pipeline/clipseg/score.py
pipeline/clipseg/setup.py
pipeline/clipseg/training.py
weights/__init__.py
navigate_with_image_language_model-1.2.dist-info/METADATA
navigate_with_image_language_model-1.2.dist-info/WHEEL
navigate_with_image_language_model-1.2.dist-info/top_level.txt
navigate_with_image_language_model-1.2.dist-info/RECORD
